SimpleDataTransport/__init__.py
SimpleDataTransport/local.py
SimpleDataTransport/remote.py
SimpleDataTransport-1.4.dist-info/LICENSE
SimpleDataTransport-1.4.dist-info/METADATA
SimpleDataTransport-1.4.dist-info/WHEEL
SimpleDataTransport-1.4.dist-info/top_level.txt
SimpleDataTransport-1.4.dist-info/RECORD
